lemmy/__init__.py
lemmy/cli/__init__.py
lemmy/cli/__main__.py
lemmy/lemmatizer.py
lemmy/pipe/__init__.py
lemmy/pipe/component.py
lemmy/serialization.py
lemmy/version.py
lemmy3-3.2.0a0.dist-info/entry_points.txt
lemmy3-3.2.0a0.dist-info/LICENSE
lemmy3-3.2.0a0.dist-info/WHEEL
lemmy3-3.2.0a0.dist-info/METADATA
lemmy3-3.2.0a0.dist-info/RECORD
